easierfile/__init__.py
easierfile/file.py
easierfile-3.0.0.dist-info/LICENSE
easierfile-3.0.0.dist-info/METADATA
easierfile-3.0.0.dist-info/WHEEL
easierfile-3.0.0.dist-info/RECORD
