Metadata-Version: 2.1
Name: easierfile
Version: 3.0.0
Summary: An easier-to-use Python package that object-oriented encapsulates Python traditional built-in file operations.
Home-page: https://github.com/leoweyr/Python-Easierfile
License: MIT
Author: leoweyr
Author-email: leoweyr@foxmail.com
Requires-Python: >=3.8,<4.0
Classifier: Development Status :: 4 - Beta
Classifier: License :: OSI Approved :: MIT License
Classifier: Programming Language :: Python :: 3
Classifier: Programming Language :: Python :: 3.8
Classifier: Programming Language :: Python :: 3.9
Classifier: Programming Language :: Python :: 3.10
Classifier: Programming Language :: Python :: 3.11
Requires-Dist: chardet (>=5.1.0,<6.0.0)
Requires-Dist: dynoptimdict (>=2.0.0,<3.0.0)
Project-URL: Repository, https://github.com/leoweyr/Python-Easierfile
